MANIFEST.in
README.md
setup.py
sibus_lib/CoreDatabase.py
sibus_lib/DefaultLogger.py
sibus_lib/MessagingCore.py
sibus_lib/SmartConfig.py
sibus_lib/__init__.py
sibus_lib/utils.py
sibus_lib.egg-info/PKG-INFO
sibus_lib.egg-info/SOURCES.txt
sibus_lib.egg-info/dependency_links.txt
sibus_lib.egg-info/entry_points.txt
sibus_lib.egg-info/requires.txt
sibus_lib.egg-info/top_level.txt
sibus_lib/resources/sibus.yml