Metadata-Version: 1.1
Name: sibus-lib
Version: 0.2.2
Summary: Library for SiBus elements
Home-page: https://github.com/picusalex/sibus_lib
Author: PicusAlex
Author-email: picusalex@yahoo.fr
License: WTFPL
Platform: UNKNOWN
Classifier: Programming Language :: Python
Classifier: Development Status :: 1 - Planning
Classifier: License :: OSI Approved
Classifier: Natural Language :: French
Classifier: Operating System :: OS Independent
Classifier: Programming Language :: Python :: 2.7
Classifier: Topic :: Communications
